autologbook/__init__.py
autologbook/__main__.py
autologbook/about_dialog_ui.py
autologbook/attachment.py
autologbook/autocli.py
autologbook/autoconfig.py
autologbook/autoerror.py
autologbook/autogui.py
autologbook/autologbook_app.py
autologbook/autoprotocol.py
autologbook/autotools.py
autologbook/autowatchdog.py
autologbook/change_sample_dialog_ui.py
autologbook/configuration_editor_ui.py
autologbook/containers.py
autologbook/context_menu.py
autologbook/dialog_windows.py
autologbook/edit_lock_dialog_ui.py
autologbook/elog_interface.py
autologbook/elog_post_splitter.py
autologbook/file_system_command.py
autologbook/file_type_guesser.py
autologbook/html_helpers.py
autologbook/jinja_integration.py
autologbook/main_window_ui.py
autologbook/microscope_picture.py
autologbook/model_test_ui.py
autologbook/navigation_image.py
autologbook/object_factoy.py
autologbook/optical_image.py
autologbook/protocol_editor.py
autologbook/protocol_editor_models.py
autologbook/protocol_editor_ui.py
autologbook/qt_signal_dispatcher.py
autologbook/rename_dialog_ui.py
autologbook/resource_rc.py
autologbook/resource_rc.rcc
autologbook/restore_element.py
autologbook/restore_element_dialog_ui.py
autologbook/sample.py
autologbook/thread_worker.py
autologbook/user_editor_ui.py
autologbook/video.py
autologbook/conf/type_guesser_regexp.yaml
autologbook/templates/attachment_base_template.yammy
autologbook/templates/digital_camera_optical_image_gps_template.yammy
autologbook/templates/digital_camera_optical_image_template.yammy
autologbook/templates/empty_page_template.yammy
autologbook/templates/fei_microscope_picture_template.yammy
autologbook/templates/footer_base_template.yammy
autologbook/templates/general_attachment_base_template.yammy
autologbook/templates/general_optical_images_base_template.yammy
autologbook/templates/keyence_optical_image_template.yammy
autologbook/templates/macros.yammy
autologbook/templates/microscope_list_post_base_template.yammy
autologbook-0.1.8.dist-info/METADATA
autologbook-0.1.8.dist-info/WHEEL
autologbook-0.1.8.dist-info/entry_points.txt
autologbook-0.1.8.dist-info/licenses/LICENSE.txt
autologbook-0.1.8.dist-info/RECORD
