Metadata-Version: 2.3
Name: autologbook
Version: 0.1.8
Summary: A python toolkit for the automatic generation of elog entries of SEM analysis.
Project-URL: Homepage, https://github.com/abulgher/autologbook
Author-email: Antonio Bulgheroni <antonio.bulgheroni@gmail.com>
License: Copyright (c) 2022 Antonio Bulgheroni
License-File: LICENSE.txt
Classifier: License :: OSI Approved :: MIT License
Classifier: Operating System :: Microsoft :: Windows
Classifier: Programming Language :: Python :: 3
Requires-Python: >=3.10.5
Requires-Dist: beautifulsoup4==4.11.1
Requires-Dist: certifi
Requires-Dist: charset-normalizer~=2.1.0
Requires-Dist: defusedxml==0.7.1
Requires-Dist: idna==3.4
Requires-Dist: jinja2==3.1.2
Requires-Dist: lxml==4.9.1
Requires-Dist: markdown==3.4.1
Requires-Dist: numpy==1.23.3
Requires-Dist: passlib==1.7.4
Requires-Dist: piexif==1.1.3
Requires-Dist: pillow>=9.3.0
Requires-Dist: py-elog>=1.3.16
Requires-Dist: pyqt5-qt5==5.15.2
Requires-Dist: pyqt5-sip==12.11.0
Requires-Dist: pyqt5==5.15.7
Requires-Dist: python-dateutil==2.8.2
Requires-Dist: pyyaml==6.0
Requires-Dist: requests==2.28.1
Requires-Dist: six==1.16.0
Requires-Dist: soupsieve==2.3.2.post1
Requires-Dist: tenacity==8.0.1
Requires-Dist: urllib3==1.26.12
Requires-Dist: watchdog>=2.1.9
Requires-Dist: yammy==0.5.4
